geodetic.cpython-310-darwin.so
planar.cpython-310-darwin.so
boxdist/__init__.py
boxdist/__init__.pyi
boxdist/py.typed
boxdist-1.3.1.dist-info/LICENSE
boxdist-1.3.1.dist-info/METADATA
boxdist-1.3.1.dist-info/WHEEL
boxdist-1.3.1.dist-info/top_level.txt
boxdist-1.3.1.dist-info/RECORD
