Metadata-Version: 2.1
Name: boxdist
Version: 1.3.1
Summary: Cythonized geodetic and planar distance functions for R-Trees.
Home-page: https://github.com/invisiblefunnel/boxdist
Author: Danny Whalen
Author-email: daniel.r.whalen@gmail.com
License: MIT
Classifier: Programming Language :: Python :: 3
Classifier: License :: OSI Approved :: MIT License
Classifier: Operating System :: OS Independent
Requires-Python: >=3
License-File: LICENSE
Provides-Extra: tests
Requires-Dist: haversine ; extra == 'tests'
Requires-Dist: geojson ; extra == 'tests'
Requires-Dist: mypy ; extra == 'tests'
